{"monsters": [{"flock": 62, "id:": 1, "treasure_type": 0, "unknown": 0, "energy": 24, "speed": 16, "experience": 59, "name": "A Water Leaper", "strength": 12, "brains": 14}, {"flock": 73, "id:": 2, "treasure_type": 0, "unknown": 0, "energy": 30, "speed": 29, "experience": 66, "name": "A Leech", "strength": 4, "brains": 19}, {"flock": 3, "id:": 3, "treasure_type": 1, "unknown": 0, "energy": 46, "speed": 15, "experience": 127, "name": "An Urisk", "strength": 13, "brains": 30}, {"flock": 0, "id:": 4, "treasure_type": 2, "unknown": 0, "energy": 63, "speed": 18, "experience": 226, "name": "Shellycoat", "strength": 28, "brains": 21}, {"flock": 11, "id:": 5, "treasure_type": 2, "unknown": 0, "energy": 58, "speed": 27, "experience": 378, "name": "A Naiad", "strength": 21, "brains": 62}, {"flock": 6, "id:": 6, "treasure_type": 3, "unknown": 0, "energy": 108, "speed": 28, "experience": 604, "name": "A Nixie", "strength": 22, "brains": 58}, {"flock": 0, "id:": 7, "treasure_type": 3, "unknown": 0, "energy": 127, "speed": 25, "experience": 1002, "name": "A Glaistig", "strength": 21, "brains": 106}, {"flock": 0, "id:": 8, "treasure_type": 3, "unknown": 0, "energy": 108, "speed": 22, "experience": 809, "name": "A Mermaid", "strength": 18, "brains": 116}, {"flock": 0, "id:": 9, "treasure_type": 4, "unknown": 0, "energy": 109, "speed": 23, "experience": 808, "name": "A Merman", "strength": 24, "brains": 115}, {"flock": 24, "id:": 10, "treasure_type": 4, "unknown": 0, "energy": 89, "speed": 31, "experience": 915, "name": "A Siren", "strength": 22, "brains": 128}, {"flock": 37, "id:": 11, "treasure_type": 4, "unknown": 15, "energy": 156, "speed": 33, "experience": 1562, "name": "A Lamprey", "strength": 14, "brains": 67}, {"flock": 20, "id:": 12, "treasure_type": 5, "unknown": 0, "energy": 206, "speed": 26, "experience": 2006, "name": "A Kopoacinth", "strength": 26, "brains": 36}, {"flock": 0, "id:": 13, "treasure_type": 5, "unknown": 0, "energy": 223, "speed": 24, "experience": 4025, "name": "A Kelpie", "strength": 61, "brains": 25}, {"flock": 2, "id:": 14, "treasure_type": 7, "unknown": 0, "energy": 898, "speed": 19, "experience": 10041, "name": "An Aspidchelone", "strength": 114, "brains": 104}, {"flock": 0, "id:": 15, "treasure_type": 0, "unknown": 28, "energy": 28, "speed": 16, "experience": 49, "name": "An Idiot", "strength": 13, "brains": 14}, {"flock": 12, "id:": 16, "treasure_type": 5, "unknown": 2, "energy": 40, "speed": 20, "experience": 101, "name": "Modnar", "strength": 15, "brains": 23}, {"flock": 100, "id:": 17, "treasure_type": 0, "unknown": 30, "energy": 10, "speed": 10, "experience": 28, "name": "A Moron", "strength": 3, "brains": 1}, {"flock": 26, "id:": 18, "treasure_type": 0, "unknown": 0, "energy": 100, "speed": 45, "experience": 57, "name": "Some Green Slime", "strength": 1, "brains": 5}, {"flock": 32, "id:": 19, "treasure_type": 0, "unknown": 0, "energy": 26, "speed": 23, "experience": 64, "name": "A Pixie", "strength": 11, "brains": 29}, {"flock": 10, "id:": 20, "treasure_type": 0, "unknown": 0, "energy": 25, "speed": 25, "experience": 79, "name": "A Serpent", "strength": 10, "brains": 18}, {"flock": 5, "id:": 21, "treasure_type": 0, "unknown": 14, "energy": 30, "speed": 20, "experience": 81, "name": "A Cluricaun", "strength": 12, "brains": 27}, {"flock": 1, "id:": 22, "treasure_type": 0, "unknown": 0, "energy": 40, "speed": 14, "experience": 92, "name": "An Imp", "strength": 22, "brains": 30}, {"flock": 61, "id:": 23, "treasure_type": 0, "unknown": 0, "energy": 15, "speed": 18, "experience": 33, "name": "A Centipede", "strength": 3, "brains": 8}, {"flock": 48, "id:": 24, "treasure_type": 0, "unknown": 0, "energy": 26, "speed": 21, "experience": 44, "name": "A Beetle", "strength": 2, "brains": 11}, {"flock": 1, "id:": 25, "treasure_type": 0, "unknown": 14, "energy": 35, "speed": 17, "experience": 107, "name": "A Fir Darrig", "strength": 18, "brains": 22}, {"flock": 21, "id:": 26, "treasure_type": 0, "unknown": 0, "energy": 23, "speed": 26, "experience": 111, "name": "A Gnome", "strength": 7, "brains": 45}, {"flock": 43, "id:": 27, "treasure_type": 1, "unknown": 0, "energy": 31, "speed": 25, "experience": 132, "name": "A Sprite", "strength": 9, "brains": 37}, {"flock": 0, "id:": 28, "treasure_type": 1, "unknown": 3, "energy": 47, "speed": 20, "experience": 213, "name": "A Mimic", "strength": 9, "brains": 55}, {"flock": 68, "id:": 29, "treasure_type": 1, "unknown": 12, "energy": 21, "speed": 14, "experience": 121, "name": "A Kobold", "strength": 13, "brains": 10}, {"flock": 57, "id:": 30, "treasure_type": 1, "unknown": 15, "energy": 28, "speed": 28, "experience": 154, "name": "A Spider", "strength": 6, "brains": 11}, {"flock": 6, "id:": 31, "treasure_type": 1, "unknown": 0, "energy": 32, "speed": 21, "experience": 93, "name": "An Uldra", "strength": 14, "brains": 37}, {"flock": 81, "id:": 32, "treasure_type": 1, "unknown": 0, "energy": 31, "speed": 31, "experience": 112, "name": "A Crebain", "strength": 5, "brains": 11}, {"flock": 15, "id:": 33, "treasure_type": 1, "unknown": 14, "energy": 35, "speed": 16, "experience": 157, "name": "A Bogle", "strength": 19, "brains": 15}, {"flock": 10, "id:": 34, "treasure_type": 1, "unknown": 14, "energy": 45, "speed": 15, "experience": 139, "name": "A Fachan", "strength": 9, "brains": 40}, {"flock": 95, "id:": 35, "treasure_type": 1, "unknown": 0, "energy": 25, "speed": 35, "experience": 101, "name": "A Stirge", "strength": 2, "brains": 6}, {"flock": 2, "id:": 36, "treasure_type": 2, "unknown": 14, "energy": 28, "speed": 13, "experience": 104, "name": "A Ghillie Dhu", "strength": 12, "brains": 16}, {"flock": 0, "id:": 37, "treasure_type": 2, "unknown": 16, "energy": 9, "speed": 27, "experience": 213, "name": "A Shrieker", "strength": 2, "brains": 62}, {"flock": 36, "id:": 38, "treasure_type": 2, "unknown": 0, "energy": 51, "speed": 23, "experience": 136, "name": "A Trow", "strength": 15, "brains": 17}, {"flock": 42, "id:": 39, "treasure_type": 2, "unknown": 0, "energy": 65, "speed": 20, "experience": 142, "name": "A Carrion Crawler", "strength": 12, "brains": 20}, {"flock": 61, "id:": 40, "treasure_type": 2, "unknown": 0, "energy": 40, "speed": 15, "experience": 166, "name": "A Gnoll", "strength": 20, "brains": 25}, {"flock": 57, "id:": 41, "treasure_type": 2, "unknown": 29, "energy": 57, "speed": 19, "experience": 189, "name": "A Smurf", "strength": 23, "brains": 28}, {"flock": 88, "id:": 42, "treasure_type": 2, "unknown": 0, "energy": 45, "speed": 17, "experience": 152, "name": "A Warg", "strength": 20, "brains": 10}, {"flock": 92, "id:": 43, "treasure_type": 2, "unknown": 0, "energy": 26, "speed": 16, "experience": 141, "name": "An Orc", "strength": 25, "brains": 13}, {"flock": 22, "id:": 44, "treasure_type": 3, "unknown": 14, "energy": 75, "speed": 8, "experience": 175, "name": "A Killmoulis", "strength": 30, "brains": 19}, {"flock": 18, "id:": 45, "treasure_type": 3, "unknown": 0, "energy": 72, "speed": 15, "experience": 246, "name": "A Hob-goblin", "strength": 35, "brains": 20}, {"flock": 8, "id:": 46, "treasure_type": 3, "unknown": 0, "energy": 61, "speed": 25, "experience": 300, "name": "A Wichtlein", "strength": 13, "brains": 40}, {"flock": 42, "id:": 47, "treasure_type": 3, "unknown": 0, "energy": 65, "speed": 21, "experience": 222, "name": "A Fenoderee", "strength": 16, "brains": 6}, {"flock": 1, "id:": 48, "treasure_type": 3, "unknown": 14, "energy": 55, "speed": 19, "experience": 387, "name": "A Bwca", "strength": 21, "brains": 17}, {"flock": 19, "id:": 49, "treasure_type": 3, "unknown": 0, "energy": 115, "speed": 16, "experience": 409, "name": "An Ogre", "strength": 42, "brains": 14}, {"flock": 3, "id:": 50, "treasure_type": 3, "unknown": 0, "energy": 76, "speed": 11, "experience": 563, "name": "A Dodo", "strength": 62, "brains": 12}, {"flock": 27, "id:": 51, "treasure_type": 3, "unknown": 0, "energy": 99, "speed": 33, "experience": 599, "name": "A Hydra", "strength": 14, "brains": 27}, {"flock": 12, "id:": 52, "treasure_type": 3, "unknown": 0, "energy": 62, "speed": 26, "experience": 426, "name": "A Hamadryad", "strength": 23, "brains": 47}, {"flock": 0, "id:": 53, "treasure_type": 4, "unknown": 1, "energy": 57, "speed": 99, "experience": 669, "name": "A Unicorn", "strength": 27, "brains": 57}, {"flock": 22, "id:": 54, "treasure_type": 4, "unknown": 0, "energy": 100, "speed": 18, "experience": 623, "name": "An Owlbear", "strength": 35, "brains": 16}, {"flock": 2, "id:": 55, "treasure_type": 4, "unknown": 0, "energy": 65, "speed": 15, "experience": 786, "name": "Black Annis", "strength": 37, "brains": 52}, {"flock": 0, "id:": 56, "treasure_type": 4, "unknown": 0, "energy": 114, "speed": 12, "experience": 1191, "name": "A Jubjub Bird", "strength": 45, "brains": 23}, {"flock": 2, "id:": 57, "treasure_type": 5, "unknown": 0, "energy": 98, "speed": 24, "experience": 1300, "name": "A Peridexion", "strength": 26, "brains": 32}, {"flock": 20, "id:": 58, "treasure_type": 5, "unknown": 0, "energy": 172, "speed": 37, "experience": 1929, "name": "A Chaladrius", "strength": 8, "brains": 49}, {"flock": 4, "id:": 59, "treasure_type": 5, "unknown": 0, "energy": 65, "speed": 20, "experience": 1888, "name": "A Gwyllion", "strength": 27, "brains": 73}, {"flock": 18, "id:": 60, "treasure_type": 5, "unknown": 0, "energy": 199, "speed": 10, "experience": 263, "name": "A Cinomulgus", "strength": 23, "brains": 2}, {"flock": 13, "id:": 61, "treasure_type": 4, "unknown": 0, "energy": 264, "speed": 7, "experience": 1257, "name": "A Jello Blob", "strength": 100, "brains": 25}, {"flock": 38, "id:": 62, "treasure_type": 4, "unknown": 0, "energy": 206, "speed": 24, "experience": 1438, "name": "A Cocodrill", "strength": 39, "brains": 28}, {"flock": 29, "id:": 63, "treasure_type": 4, "unknown": 24, "energy": 185, "speed": 20, "experience": 1013, "name": "A Troll", "strength": 75, "brains": 12}, {"flock": 14, "id:": 64, "treasure_type": 4, "unknown": 17, "energy": 255, "speed": 9, "experience": 1661, "name": "A Bonnacon", "strength": 89, "brains": 26}, {"flock": 7, "id:": 65, "treasure_type": 5, "unknown": 0, "energy": 200, "speed": 29, "experience": 1753, "name": "A Gargoyle", "strength": 22, "brains": 21}, {"flock": 0, "id:": 66, "treasure_type": 5, "unknown": 18, "energy": 373, "speed": 27, "experience": 2487, "name": "Smeagol", "strength": 41, "brains": 33}, {"flock": 13, "id:": 67, "treasure_type": 5, "unknown": 25, "energy": 200, "speed": 22, "experience": 3112, "name": "A Wraith", "strength": 52, "brains": 102}, {"flock": 12, "id:": 68, "treasure_type": 5, "unknown": 0, "energy": 300, "speed": 21, "experience": 4125, "name": "A Phooka", "strength": 42, "brains": 63}, {"flock": 4, "id:": 69, "treasure_type": 6, "unknown": 9, "energy": 500, "speed": 31, "experience": 6992, "name": "A Vortex", "strength": 101, "brains": 30}, {"flock": 3, "id:": 70, "treasure_type": 6, "unknown": 0, "energy": 525, "speed": 26, "experience": 5752, "name": "A Snotgurgle", "strength": 143, "brains": 19}, {"flock": 0, "id:": 71, "treasure_type": 6, "unknown": 7, "energy": 400, "speed": 23, "experience": 7628, "name": "A Thaumaturgist", "strength": 35, "brains": 200}, {"flock": 3, "id:": 72, "treasure_type": 6, "unknown": 0, "energy": 450, "speed": 22, "experience": 7981, "name": "A Bandersnatch", "strength": 105, "brains": 98}, {"flock": 2, "id:": 73, "treasure_type": 6, "unknown": 0, "energy": 263, "speed": 24, "experience": 7582, "name": "A Harpy", "strength": 103, "brains": 49}, {"flock": 3, "id:": 74, "treasure_type": 6, "unknown": 0, "energy": 809, "speed": 17, "experience": 7777, "name": "A Tigris", "strength": 182, "brains": 38}, {"flock": 2, "id:": 75, "treasure_type": 6, "unknown": 0, "energy": 585, "speed": 18, "experience": 8333, "name": "A Coblynau", "strength": 205, "brains": 46}, {"flock": 0, "id:": 76, "treasure_type": 7, "unknown": 13, "energy": 628, "speed": 28, "experience": 9003, "name": "Shelob", "strength": 147, "brains": 64}, {"flock": 1, "id:": 77, "treasure_type": 7, "unknown": 0, "energy": 813, "speed": 19, "experience": 8888, "name": "A Gryphon", "strength": 201, "brains": 45}, {"flock": 0, "id:": 78, "treasure_type": 7, "unknown": 0, "energy": 947, "speed": 28, "experience": 10006, "name": "A Chimaera", "strength": 173, "brains": 109}, {"flock": 0, "id:": 79, "treasure_type": 7, "unknown": 0, "energy": 1000, "speed": 12, "experience": 8119, "name": "A Jack-in-Irons", "strength": 222, "brains": 36}, {"flock": 0, "id:": 80, "treasure_type": 7, "unknown": 0, "energy": 1022, "speed": 26, "experience": 10077, "name": "Smaug", "strength": 251, "brains": 76}, {"flock": 0, "id:": 81, "treasure_type": 7, "unknown": 8, "energy": 705, "speed": 25, "experience": 10103, "name": "A Balrog", "strength": 500, "brains": 100}, {"flock": 0, "id:": 82, "treasure_type": 7, "unknown": 0, "energy": 1500, "speed": 14, "experience": 9510, "name": "Argus", "strength": 201, "brains": 87}, {"flock": 0, "id:": 83, "treasure_type": 7, "unknown": 0, "energy": 1750, "speed": 19, "experience": 11012, "name": "Cacus", "strength": 256, "brains": 43}, {"flock": 0, "id:": 84, "treasure_type": 8, "unknown": 0, "energy": 1222, "speed": 24, "experience": 10888, "name": "A Cold-drake", "strength": 301, "brains": 102}, {"flock": 0, "id:": 85, "treasure_type": 8, "unknown": 0, "energy": 1875, "speed": 10, "experience": 12013, "name": "Begion", "strength": 403, "brains": 154}, {"flock": 0, "id:": 86, "treasure_type": 8, "unknown": 0, "energy": 1299, "speed": 23, "experience": 13649, "name": "A Red Dragon", "strength": 342, "brains": 141}, {"flock": 0, "id:": 87, "treasure_type": 8, "unknown": 0, "energy": 2000, "speed": 23, "experience": 14014, "name": "Grendel", "strength": 197, "brains": 262}, {"flock": 0, "id:": 88, "treasure_type": 8, "unknown": 0, "energy": 1965, "speed": 35, "experience": 15111, "name": "Red Cap", "strength": 143, "brains": 50}, {"flock": 0, "id:": 89, "treasure_type": 8, "unknown": 0, "energy": 2185, "speed": 20, "experience": 15555, "name": "A Nuckelavee", "strength": 300, "brains": 75}, {"flock": 0, "id:": 90, "treasure_type": 8, "unknown": 26, "energy": 1625, "speed": 12, "experience": 16016, "name": "A Titan", "strength": 302, "brains": 1483}, {"flock": 0, "id:": 91, "treasure_type": 11, "unknown": 6, "energy": 1500, "speed": 17, "experience": 17101, "name": "Saruman", "strength": 55, "brains": 373}, {"flock": 9, "id:": 92, "treasure_type": 10, "unknown": 10, "energy": 1011, "speed": 26, "experience": 12988, "name": "A Nazgul", "strength": 250, "brains": 251}, {"flock": 0, "id:": 93, "treasure_type": 9, "unknown": 0, "energy": 1790, "speed": 20, "experience": 17999, "name": "Scatha the Worm", "strength": 406, "brains": 208}, {"flock": 0, "id:": 94, "treasure_type": 9, "unknown": 11, "energy": 2000, "speed": 29, "experience": 19001, "name": "Tiamat", "strength": 506, "brains": 381}, {"flock": 0, "id:": 95, "treasure_type": 9, "unknown": 22, "energy": 2265, "speed": 25, "experience": 19984, "name": "A Jabberwock", "strength": 185, "brains": 136}, {"flock": 0, "id:": 96, "treasure_type": 9, "unknown": 19, "energy": 2007, "speed": 27, "experience": 23256, "name": "A Succubus", "strength": 186, "brains": 1049}, {"flock": 0, "id:": 97, "treasure_type": 9, "unknown": 20, "energy": 2600, "speed": 29, "experience": 25862, "name": "Cerberus", "strength": 236, "brains": 96}, {"flock": 0, "id:": 98, "treasure_type": 12, "unknown": 21, "energy": 2784, "speed": 37, "experience": 27849, "name": "Ungoliant", "strength": 399, "brains": 2398}, {"flock": 0, "id:": 99, "treasure_type": 13, "unknown": 5, "energy": 3000, "speed": 46, "experience": 30004, "name": "Leanan-Sidhe", "strength": 486, "brains": 5432}, {"flock": 0, "id:": 100, "treasure_type": 14, "unknown": 4, "energy": 19999, "speed": 31, "experience": 40005, "name": "The Dark Lord", "strength": 9999, "brains": 9999}], "data": "monsters"}